livepyxel/__init__.py
livepyxel/__main__.py
livepyxel/bezierman.py
livepyxel/binaman.py
livepyxel/bucketman.py
livepyxel/constants.py
livepyxel/edit_label_box.py
livepyxel/freehandman.py
livepyxel/imageAnnotator.py
livepyxel/polyman.py
livepyxel/ui_main_window.py
livepyxel/video_device_manager.py
livepyxel/warning_dialog_delete.py
livepyxel/icons/additiveOFF_icon.png
livepyxel/icons/additive_icon.png
livepyxel/icons/bezier_icon.png
livepyxel/icons/binmask_icon.png
livepyxel/icons/bright_cross_cursor.png
livepyxel/icons/brush_icon.png
livepyxel/icons/bucket_icon.png
livepyxel/icons/editFolder_icon.png
livepyxel/icons/edit_icon.png
livepyxel/icons/fail_icon.png
livepyxel/icons/freehand_icon.png
livepyxel/icons/gif_view.gif
livepyxel/icons/main.ai
livepyxel/icons/main_logo.ai
livepyxel/icons/main_logo.png
livepyxel/icons/main_logo_long.png
livepyxel/icons/next_icon.png
livepyxel/icons/openFolder_icon.png
livepyxel/icons/polygon_icon.png
livepyxel/icons/prev_icon.png
livepyxel/icons/simple_bw.ai
livepyxel/icons/success_icon.png
livepyxel/icons/topmask_OFF_icon.png
livepyxel/icons/topmask_ON_icon.png
livepyxel/icons/trash_icon.png
livepyxel/icons/warning_icon.png
livepyxel-0.1.3.dist-info/licenses/LICENSE
livepyxel-0.1.3.dist-info/METADATA
livepyxel-0.1.3.dist-info/WHEEL
livepyxel-0.1.3.dist-info/entry_points.txt
livepyxel-0.1.3.dist-info/top_level.txt
livepyxel-0.1.3.dist-info/RECORD
