Metadata-Version: 2.4
Name: livepyxel
Version: 0.1.3
Summary: A GUI tool for dataset preparation / annotation (instance segmentation & ML)
Author-email: Uriel Garcilazo Cruz <garcilazo.uriel@gmail.com>
License: LICENSE
Project-URL: Homepage, https://ugarcil.github.io/LivePyxel/
Project-URL: Issues, https://github.com/UGarCil/LivePyxel/issues
Keywords: annotation,computer-vision,opencv,pyqt5,gui
Classifier: Programming Language :: Python :: 3
Classifier: License :: OSI Approved :: MIT License
Classifier: Operating System :: OS Independent
Classifier: Environment :: X11 Applications :: Qt
Classifier: Topic :: Scientific/Engineering :: Image Processing
Requires-Python: >=3.9
License-File: LICENSE
Requires-Dist: PyQt5>=5.15
Requires-Dist: opencv-python>=4.5
Provides-Extra: dev
Requires-Dist: pytest; extra == "dev"
Requires-Dist: ruff; extra == "dev"
Requires-Dist: black; extra == "dev"
Requires-Dist: build; extra == "dev"
Requires-Dist: twine; extra == "dev"
Dynamic: license-file
